cisco_deviot/__init__.py
cisco_deviot/gateway.py
cisco_deviot/mqtt_connector.py
cisco_deviot/thing.py
cisco_deviot-0.1.2.dist-info/DESCRIPTION.rst
cisco_deviot-0.1.2.dist-info/METADATA
cisco_deviot-0.1.2.dist-info/RECORD
cisco_deviot-0.1.2.dist-info/WHEEL
cisco_deviot-0.1.2.dist-info/metadata.json
cisco_deviot-0.1.2.dist-info/pbr.json
cisco_deviot-0.1.2.dist-info/top_level.txt
